virtual_lanes/__init__.py
virtual_lanes/__main__.py
virtual_lanes/alley.py
virtual_lanes/bowler.py
virtual_lanes/bowling_database.py
virtual_lanes/game.py
virtual_lanes/league.py
virtual_lanes/scoring.py
virtual_lanes/tournament.py
virtual_lanes/cli/__init__.py
virtual_lanes/cli/commands.py
virtual_lanes/tui/__init__.py
virtual_lanes/tui/app.py
virtual_lanes/web/__init__.py
virtual_lanes/web/app.py
virtual_lanes-0.2.3.dist-info/licenses/LICENSE
virtual_lanes-0.2.3.dist-info/METADATA
virtual_lanes-0.2.3.dist-info/WHEEL
virtual_lanes-0.2.3.dist-info/entry_points.txt
virtual_lanes-0.2.3.dist-info/top_level.txt
virtual_lanes-0.2.3.dist-info/RECORD
