Metadata-Version: 2.4
Name: virtual-lanes
Version: 0.2.3
Summary: A ten-pin bowling simulation library for modeling games
Author-email: Michael Borck <michael@borck.me>
License-Expression: MIT
Requires-Python: >=3.10
License-File: LICENSE
Requires-Dist: numpy>=1.26.4
Requires-Dist: typer>=0.9.0
Requires-Dist: rich>=13.7.0
Requires-Dist: textual>=0.52.1
Requires-Dist: python-fasthtml>=0.8.2
Dynamic: license-file
